pyssam/__init__.py
pyssam/datasets.py
pyssam/morph_mesh.py
pyssam/sam.py
pyssam/ssam.py
pyssam/ssm.py
pyssam/statistical_model_base.py
pyssam/utils.py
pyssam-0.2.3.dist-info/LICENSE
pyssam-0.2.3.dist-info/METADATA
pyssam-0.2.3.dist-info/WHEEL
pyssam-0.2.3.dist-info/top_level.txt
pyssam-0.2.3.dist-info/RECORD
