Metadata-Version: 2.1
Name: pyssam
Version: 0.2.3
Summary: A Python library for statistical modelling of biomedical shape and appearance
Author: Josh Williams
Project-URL: Homepage, https://github.com/jvwilliams23/pyssam
Project-URL: Bug Tracker, https://github.com/jvwilliams23/pyssam/issues
Classifier: Programming Language :: Python :: 3
Requires-Python: >=3.7
License-File: LICENSE
Requires-Dist: numpy <2.0,>1.23
Requires-Dist: scikit-learn ==1.2.0
Requires-Dist: scikit-image ==0.19.2
Requires-Dist: networkx ==2.5
Requires-Dist: vedo <=2023.4.6
Requires-Dist: trimesh
